MANIFEST.in
README.markdown
setup.cfg
setup.py
losser/__init__.py
losser/cli.py
losser/losser.py
losser/test_cli.py
losser/test_losser.py
losser.egg-info/PKG-INFO
losser.egg-info/SOURCES.txt
losser.egg-info/dependency_links.txt
losser.egg-info/entry_points.txt
losser.egg-info/requires.txt
losser.egg-info/top_level.txt