Metadata-Version: 1.1
Name: losser
Version: 0.0.3
Summary: Filter, transform and export a list of JSON objects to JSON or CSV
Home-page: https://github.com/ckan/losser
Author: Sean Hammond
Author-email: losser@seanh.cc
License: AGPL
Keywords: json csv
Platform: UNKNOWN
Classifier: Development Status :: 4 - Beta
Classifier: License :: OSI Approved :: GNU Affero General Public License v3 or later (AGPLv3+)
Classifier: Programming Language :: Python :: 2.7
